<?xml version="1.0" encoding="utf-8"?>
<openerp>
    <data>
    
		<menuitem id="menu_action_bang_gia"
			action="action_bang_gia"
			name="Bảng giá"
			parent="menu_config_hopdong" sequence="20"/>
			
    	<record model="ir.ui.menu" id="base.menu_config_address_book">
	    	<field name="groups_id" eval="[(4, ref('green_erp_viruco_base.group_viruco_admin'))]"/>
		</record>
		<record model="ir.ui.menu" id="base.menu_country_partner">
	    	<field name="groups_id" eval="[(4, ref('green_erp_viruco_base.group_viruco_admin'))]"/>
		</record>
		<record model="ir.ui.menu" id="base.menu_country_state_partner">
	    	<field name="groups_id" eval="[(4, ref('green_erp_viruco_base.group_viruco_admin'))]"/>
		</record>
		<record model="ir.ui.menu" id="base.menu_localisation">
	    	<field name="groups_id" eval="[(4, ref('green_erp_viruco_base.group_viruco_admin'))]"/>
		</record>
    </data>
</openerp>
