<?xml version="1.0" encoding="utf-8"?>
<openerp>
    <data noupdate='1'>
		<record id="loaivat_bosua" model="loai.vat">
            <field name="name">Bò Sữa</field>
            <field name="ma_loai">bo_sua</field>
        </record>
        
        <record id="chitiet_bosua_duc" model="chi.tiet.loai.vat">
            <field name="name">Bò sữa đực</field>
            <field name="loai_id" ref="loaivat_bosua"/>
        </record>
        
        <record id="chitiet_bosua_cai_6_thang" model="chi.tiet.loai.vat">
            <field name="name">Bò sữa cái &lt; 6 tháng</field>
            <field name="loai_id" ref="loaivat_bosua"/>
        </record>
        
        <record id="chitiet_bosua_cai_to" model="chi.tiet.loai.vat">
            <field name="name">Bò sữa cái tơ</field>
            <field name="loai_id" ref="loaivat_bosua"/>
        </record>
        
        <record id="chitiet_bosua_cai_sinhsan" model="chi.tiet.loai.vat">
            <field name="name">Bò sữa cái sinh sản</field>
            <field name="loai_id" ref="loaivat_bosua"/>
        </record>
 
 		<record id="loaivat_bota" model="loai.vat">
            <field name="name">Bò Ta</field>
            <field name="ma_loai">bo_ta</field>
        </record>
        
        <record id="chitiet_bota_duoi_6thang" model="chi.tiet.loai.vat">
            <field name="name">Bò ta &lt; 6 tháng</field>
            <field name="loai_id" ref="loaivat_bota"/>
        </record>
        
        <record id="chitiet_bota_tren_6_thang" model="chi.tiet.loai.vat">
            <field name="name">Bò ta &gt; 6 tháng</field>
            <field name="loai_id" ref="loaivat_bota"/>
        </record>
        
 		<record id="loaivat_bolai" model="loai.vat">
            <field name="name">Bò lai sind</field>
            <field name="ma_loai">bo_lai_sind</field>
        </record>
        
        <record id="chitiet_bolai_duoi_6thang" model="chi.tiet.loai.vat">
            <field name="name">Bò lai sind &lt; 6 tháng</field>
            <field name="loai_id" ref="loaivat_bolai"/>
        </record>
        
        <record id="chitiet_bolai_tren_6thang" model="chi.tiet.loai.vat">
            <field name="name">Bò lai sind &gt; 6 tháng</field>
            <field name="loai_id" ref="loaivat_bolai"/>
        </record>
        
 		<record id="loaivat_trau" model="loai.vat">
            <field name="name">Trâu</field>
            <field name="ma_loai">trau</field>
        </record>
        
        <record id="chitiet_trau_duoi_6thang" model="chi.tiet.loai.vat">
            <field name="name">Trâu &lt; 6 tháng</field>
            <field name="loai_id" ref="loaivat_trau"/>
        </record>
        
        <record id="chitiet_trau_tren_6thang" model="chi.tiet.loai.vat">
            <field name="name">Trâu &gt; 6 tháng</field>
            <field name="loai_id" ref="loaivat_trau"/>
        </record>       

 		<record id="loaivat_de" model="loai.vat">
            <field name="name">Dê</field>
            <field name="ma_loai">de</field>
        </record>
        
 		<record id="loaivat_cuu" model="loai.vat">
            <field name="name">Cừu</field>
            <field name="ma_loai">cuu</field>
        </record>        
        
		<record id="loaivat_duc_lammviec" model="loai.vat">
            <field name="name">Đực làm việc</field>
            <field name="ma_loai">duc_lamviec</field>
        </record>
        
		<record id="loaivat_heo_haubi" model="loai.vat">
            <field name="name">Heo hậu bị</field>
            <field name="ma_loai">heo_haubi</field>
        </record>        
        
        <record id="chitiet_heo_haubi_duc" model="chi.tiet.loai.vat">
            <field name="name">Đực</field>
            <field name="loai_id" ref="loaivat_heo_haubi"/>
        </record>
        
        <record id="chitiet_heo_haubi_cai" model="chi.tiet.loai.vat">
            <field name="name">Cái</field>
            <field name="loai_id" ref="loaivat_heo_haubi"/>
        </record>

		<record id="loaivat_nai_sinhsan" model="loai.vat">
            <field name="name">Nái sinh sản</field>
            <field name="ma_loai">nai_sinhsan</field>
        </record>        
        
        <record id="chitiet_nai_kho" model="chi.tiet.loai.vat">
            <field name="name">Kho</field>
            <field name="loai_id" ref="loaivat_nai_sinhsan"/>
        </record>
        
        <record id="chitiet_nai_mangthai" model="chi.tiet.loai.vat">
            <field name="name">Mang thai</field>
            <field name="loai_id" ref="loaivat_nai_sinhsan"/>
        </record>

        <record id="chitiet_nai_nuoicon" model="chi.tiet.loai.vat">
            <field name="name">Nuôi con</field>
            <field name="loai_id" ref="loaivat_nai_sinhsan"/>
        </record>

		<record id="loaivat_heo_con" model="loai.vat">
            <field name="name">Heo con</field>
            <field name="ma_loai">heo_con</field>
        </record>        
        
        <record id="chitiet_heocon_theome" model="chi.tiet.loai.vat">
            <field name="name">Theo mẹ</field>
            <field name="loai_id" ref="loaivat_heo_con"/>
        </record>
        
        <record id="chitiet_heocon_caisua" model="chi.tiet.loai.vat">
            <field name="name">Cai sữa</field>
            <field name="loai_id" ref="loaivat_heo_con"/>
        </record>

		<record id="loaivat_heo_thit" model="loai.vat">
            <field name="name">Heo Thịt</field>
            <field name="ma_loai">heo_thit</field>
        </record> 
        
    </data>
</openerp>
