<?xml version="1.0" encoding="utf-8"?>
<openerp>
    <data>
		<record id="cocau_hientai_report" model="ir.actions.report.xml">
	        <field name="name">cocau_hientai_report</field>
	        <field name="type">ir.actions.report.xml</field>
	        <field name="model">cocau.hientai.form</field>
	        <field name="report_name">cocau_hientai_report</field>
	        <field name="report_type">aeroo</field>
	        <field name="in_format">oo-ods</field>
	        <field name="out_format" model="report.mimetypes" search="[('code','=','oo-xls')]"/>
	        <field name="parser_loc">green_erp_ccty_cocaudan/report/cocau_hientai_report.py</field>
	        <field name="report_rml">green_erp_ccty_cocaudan/report/cocau_hientai_report.ods</field>
	        <field name="parser_state">loc</field>
	        <field name="tml_source">file</field>
	        <field name="attachment_use" eval="0"/>
    	</record>		    
		
		<report 
			auto="True" 
			menu="False"
			id="cocau_hientai_report" 
			model="cocau.hientai.form" 
			name="cocau_hientai_report"
	        string="Thống kê cơ cấu hiện tại"
	        rml="green_erp_ccty_cocaudan/report/cocau_hientai_report.ods"/>	
    </data>
</openerp>

